swg2rst/test.py
swg2rst/converter_exceptions.py
swg2rst/swagger2rst.py
swg2rst/__init__.py
swg2rst/templates/operation.rst
swg2rst/templates/operation_response_example.rst
swg2rst/templates/operation_security.rst
swg2rst/templates/schema.rst
swg2rst/templates/security.rst
swg2rst/templates/operation_response_headers.rst
swg2rst/templates/main.rst
swg2rst/templates/header.rst
swg2rst/templates/definition.rst
swg2rst/templates/operation_responses.rst
swg2rst/templates/operation_response.rst
swg2rst/utils/rst.py
swg2rst/utils/logger.py
swg2rst/utils/exampilators.py
swg2rst/utils/__init__.py
swg2rst/swagger/security_mixin.py
swg2rst/swagger/abstract_type_object.py
swg2rst/swagger/security_definition.py
swg2rst/swagger/base_swagger_object.py
swg2rst/swagger/constants.py
swg2rst/swagger/schema_objects.py
swg2rst/swagger/schema.py
swg2rst/swagger/operation.py
swg2rst/swagger/header.py
swg2rst/swagger/parameter.py
swg2rst/swagger/response.py
swg2rst/swagger/__init__.py
swagger2rst-0.0.4.dist-info/entry_points.txt
swagger2rst-0.0.4.dist-info/RECORD
swagger2rst-0.0.4.dist-info/DESCRIPTION.rst
swagger2rst-0.0.4.dist-info/top_level.txt
swagger2rst-0.0.4.dist-info/METADATA
swagger2rst-0.0.4.dist-info/WHEEL
swagger2rst-0.0.4.dist-info/metadata.json
