Metadata-Version: 2.0
Name: swagger2rst
Version: 0.0.4
Summary: Tool for convert "Swagger" format file to "Restructured text"
Home-page: https://github.com/Arello-Mobile/swagger2rst
Author: Arello Mobile
Author-email: UNKNOWN
License: MIT
Platform: UNKNOWN
Classifier: Development Status :: 4 - Beta
Classifier: Environment :: Console
Classifier: Intended Audience :: Developers
Classifier: License :: OSI Approved :: MIT License
Classifier: Operating System :: OS Independent
Classifier: Programming Language :: Python :: 2.7
Classifier: Programming Language :: Python :: 3.3
Classifier: Programming Language :: Python :: 3.4
Classifier: Programming Language :: Python :: 3.5
Classifier: Topic :: Software Development :: Documentation
Requires-Dist: cached-property (>=1.3.0)
Requires-Dist: Jinja2 (>=2.8)
Requires-Dist: jsonschema (>=2.5.1)
Requires-Dist: PyYAML (>=3.11)
Requires-Dist: strict-rfc3339
